databaseci/__init__.py
databaseci/command.py
databaseci/createdrop.py
databaseci/curs.py
databaseci/database.py
databaseci/formatting.py
databaseci/notify.py
databaseci/paging.py
databaseci/psyco.py
databaseci/schemas.py
databaseci/tempdb.py
databaseci/urls.py
databaseci-5.8.2.dist-info/entry_points.txt
databaseci-5.8.2.dist-info/LICENSE.md
databaseci-5.8.2.dist-info/WHEEL
databaseci-5.8.2.dist-info/METADATA
databaseci-5.8.2.dist-info/RECORD
