Metadata-Version: 2.1
Name: databaseci
Version: 5.8.2
Summary: databaseci.com client
Home-page: https://databaseci.com
License: AGPL-3.0
Author: Robert Lechte
Author-email: rob@databaseci.com
Requires-Python: >=3.8,<4
Classifier: License :: OSI Approved :: GNU Affero General Public License v3
Classifier: Programming Language :: Python :: 3
Classifier: Programming Language :: Python :: 3.10
Classifier: Programming Language :: Python :: 3.8
Classifier: Programming Language :: Python :: 3.9
Requires-Dist: click
Requires-Dist: databaseciservices (>=5.2.2)
Requires-Dist: docker
Requires-Dist: migra
Requires-Dist: pendulum
Requires-Dist: psycopg2-binary
Requires-Dist: py
Requires-Dist: pyyaml
Requires-Dist: requests
Requires-Dist: schemainspect (>=3.1.1648463413)
